llm_rename.py
llm_rename-1.0.1.dist-info/LICENSE
llm_rename-1.0.1.dist-info/METADATA
llm_rename-1.0.1.dist-info/WHEEL
llm_rename-1.0.1.dist-info/entry_points.txt
llm_rename-1.0.1.dist-info/top_level.txt
llm_rename-1.0.1.dist-info/RECORD
