Metadata-Version: 2.1
Name: llm_rename
Version: 1.0.1
Summary: An `llm` plugin to assist with renameutils qcp/qmv commands.
Author-email: Yaniv Aknin <yaniv@aknin.name>
License: MIT License
Project-URL: homepage, https://github.com/yaniv-aknin/llm-rename
License-File: LICENSE
Requires-Dist: llm
Provides-Extra: test
Requires-Dist: pytest ; extra == 'test'
